<?xml version="1.0" encoding="utf-8"?>
<Grave xmlns:xsi="http://www.w3.org/2001/XMLSchema-instance" xmlns:xsd="http://www.w3.org/2001/XMLSchema">
  <Id>1837907</Id>
  <PersonRecords>
    <PersonRecord>
      <GivenNames>Rufus</GivenNames>
      <FamilyNames>Graybill</FamilyNames>
      <BirthYear>1876</BirthYear>
      <DeathYear>1941</DeathYear>
      <IsChanged>false</IsChanged>
      <IsVerified>true</IsVerified>
      <IsCityRecordWrong>false</IsCityRecordWrong>
    </PersonRecord>
  </PersonRecords>
  <Images>
    <string>https://s3.amazonaws.com/bg.ami.com/images/52b757a7b4515cea3fa1b4e8f8555f4b.jpg</string>
  </Images>
  <Latitude>45.520964</Latitude>
  <Longitude>-123.004948</Longitude>
  <IsVerified>true</IsVerified>
</Grave>