<?xml version="1.0" encoding="utf-8"?>
<Grave xmlns:xsi="http://www.w3.org/2001/XMLSchema-instance" xmlns:xsd="http://www.w3.org/2001/XMLSchema">
  <Id>2779541</Id>
  <PersonRecords>
    <PersonRecord>
      <GivenNames>B T</GivenNames>
      <FamilyNames>Smith</FamilyNames>
      <IsChanged>true</IsChanged>
      <IsVerified>true</IsVerified>
      <IsCityRecordWrong>false</IsCityRecordWrong>
    </PersonRecord>
  </PersonRecords>
  <Images>
    <string>https://s3.amazonaws.com/bg.ami.com/c/83194/b3abc75b83501f7f29afd9f396ce5916.jpg</string>
  </Images>
  <Latitude>45.520619</Latitude>
  <Longitude>-123.004275</Longitude>
  <IsVerified>true</IsVerified>
</Grave>