<?xml version="1.0" encoding="utf-8"?>
<Grave xmlns:xsi="http://www.w3.org/2001/XMLSchema-instance" xmlns:xsd="http://www.w3.org/2001/XMLSchema">
  <Id>1837709</Id>
  <PersonRecords>
    <PersonRecord>
      <GivenNames>Mathias Cooley</GivenNames>
      <FamilyNames>Steeples</FamilyNames>
      <BirthDay>26</BirthDay>
      <BirthMonth>Jan</BirthMonth>
      <BirthYear>1858</BirthYear>
      <DeathDay>23</DeathDay>
      <DeathMonth>Aug</DeathMonth>
      <DeathYear>1922</DeathYear>
      <IsChanged>false</IsChanged>
      <IsVerified>true</IsVerified>
      <IsCityRecordWrong>false</IsCityRecordWrong>
    </PersonRecord>
    <PersonRecord>
      <GivenNames>Sarah Lafferty</GivenNames>
      <FamilyNames>Steeples</FamilyNames>
      <BirthDay>10</BirthDay>
      <BirthMonth>Jul</BirthMonth>
      <BirthYear>1856</BirthYear>
      <DeathDay>3</DeathDay>
      <DeathMonth>Sep</DeathMonth>
      <DeathYear>1932</DeathYear>
      <IsChanged>false</IsChanged>
      <IsVerified>true</IsVerified>
      <IsCityRecordWrong>false</IsCityRecordWrong>
    </PersonRecord>
  </PersonRecords>
  <Images>
    <string>https://s3.amazonaws.com/bg.ami.com/images/2fb6b0db100773179134bbb132a4e8f3.jpg</string>
  </Images>
  <Latitude>45.520386</Latitude>
  <Longitude>-123.00746</Longitude>
  <IsVerified>true</IsVerified>
</Grave>