<?xml version="1.0" encoding="utf-8"?>
<Grave xmlns:xsi="http://www.w3.org/2001/XMLSchema-instance" xmlns:xsd="http://www.w3.org/2001/XMLSchema">
  <Id>1838230</Id>
  <PersonRecords>
    <PersonRecord>
      <FamilyNames>Shute</FamilyNames>
      <IsChanged>false</IsChanged>
      <IsVerified>true</IsVerified>
      <IsCityRecordWrong>false</IsCityRecordWrong>
    </PersonRecord>
  </PersonRecords>
  <Images>
    <string>https://s3.amazonaws.com/bg.ami.com/images/317510cade5c9795d630ee10d13d98ad.jpg</string>
  </Images>
  <Latitude>45.520367</Latitude>
  <Longitude>-123.006684</Longitude>
  <IsVerified>true</IsVerified>
</Grave>