<?xml version="1.0" encoding="utf-8"?>
<Grave xmlns:xsi="http://www.w3.org/2001/XMLSchema-instance" xmlns:xsd="http://www.w3.org/2001/XMLSchema">
  <Id>1837174</Id>
  <PersonRecords>
    <PersonRecord>
      <GivenNames>George</GivenNames>
      <FamilyNames>Billings</FamilyNames>
      <IsChanged>false</IsChanged>
      <IsVerified>true</IsVerified>
      <IsCityRecordWrong>false</IsCityRecordWrong>
    </PersonRecord>
  </PersonRecords>
  <Images>
    <string>https://s3.amazonaws.com/bg.ami.com/images/22607524ac94bd37f8cad9a413682216.jpg</string>
  </Images>
  <Information>CO D. 60 N.Y. Inf.</Information>
  <Latitude>45.520697</Latitude>
  <Longitude>-123.006202</Longitude>
  <IsVerified>true</IsVerified>
</Grave>