<?xml version="1.0" encoding="utf-8"?>
<Grave xmlns:xsi="http://www.w3.org/2001/XMLSchema-instance" xmlns:xsd="http://www.w3.org/2001/XMLSchema">
  <Id>1668078</Id>
  <PersonRecords>
    <PersonRecord>
      <GivenNames>Henrietta</GivenNames>
      <FamilyNames>Scholfield</FamilyNames>
      <BirthYear>1874</BirthYear>
      <DeathYear>1875</DeathYear>
      <IsChanged>false</IsChanged>
      <IsVerified>true</IsVerified>
      <IsCityRecordWrong>false</IsCityRecordWrong>
    </PersonRecord>
  </PersonRecords>
  <Images>
    <string>https://s3.amazonaws.com/bg.ami.com/images/b5ca7e3c4c84646511a543566ff1d435.jpg</string>
  </Images>
  <Latitude>45.5203</Latitude>
  <Longitude>-123.005711</Longitude>
  <IsVerified>true</IsVerified>
</Grave>