<?xml version="1.0" encoding="utf-8"?>
<Grave xmlns:xsi="http://www.w3.org/2001/XMLSchema-instance" xmlns:xsd="http://www.w3.org/2001/XMLSchema">
  <Id>1837311</Id>
  <PersonRecords>
    <PersonRecord>
      <GivenNames>Mary</GivenNames>
      <IsChanged>false</IsChanged>
      <IsVerified>true</IsVerified>
      <IsCityRecordWrong>false</IsCityRecordWrong>
    </PersonRecord>
  </PersonRecords>
  <Images>
    <string>https://s3.amazonaws.com/bg.ami.com/images/b4604a17f642b5c8e4f1d89d44b0ecd1.jpg</string>
  </Images>
  <Latitude>45.520312</Latitude>
  <Longitude>-123.00496</Longitude>
  <IsVerified>true</IsVerified>
</Grave>