<?xml version="1.0" encoding="utf-8"?>
<Grave xmlns:xsi="http://www.w3.org/2001/XMLSchema-instance" xmlns:xsd="http://www.w3.org/2001/XMLSchema">
  <Id>1837306</Id>
  <PersonRecords>
    <PersonRecord>
      <GivenNames>Richard</GivenNames>
      <IsChanged>false</IsChanged>
      <IsVerified>true</IsVerified>
      <IsCityRecordWrong>false</IsCityRecordWrong>
    </PersonRecord>
  </PersonRecords>
  <Images>
    <string>https://s3.amazonaws.com/bg.ami.com/images/5bfd8c02a26948adb4f0363a81d7aab4.jpg</string>
  </Images>
  <Latitude>45.520344</Latitude>
  <Longitude>-123.004929</Longitude>
  <IsVerified>true</IsVerified>
</Grave>