<?xml version="1.0" encoding="utf-8"?>
<Grave xmlns:xsi="http://www.w3.org/2001/XMLSchema-instance" xmlns:xsd="http://www.w3.org/2001/XMLSchema">
  <Id>1837724</Id>
  <PersonRecords>
    <PersonRecord>
      <GivenNames>Eugene</GivenNames>
      <FamilyNames>Lee</FamilyNames>
      <BirthYear>1859</BirthYear>
      <DeathYear>1951</DeathYear>
      <IsChanged>false</IsChanged>
      <IsVerified>true</IsVerified>
      <IsCityRecordWrong>false</IsCityRecordWrong>
    </PersonRecord>
  </PersonRecords>
  <Images>
    <string>https://s3.amazonaws.com/bg.ami.com/images/0d072d491103466bde4fbcfd43169055.jpg</string>
  </Images>
  <Latitude>45.520096</Latitude>
  <Longitude>-123.00748</Longitude>
  <IsVerified>true</IsVerified>
</Grave>