<?xml version="1.0" encoding="utf-8"?>
<Grave xmlns:xsi="http://www.w3.org/2001/XMLSchema-instance" xmlns:xsd="http://www.w3.org/2001/XMLSchema">
  <Id>1838437</Id>
  <PersonRecords>
    <PersonRecord>
      <GivenNames>John</GivenNames>
      <FamilyNames>McPherson</FamilyNames>
      <BirthYear>1873</BirthYear>
      <DeathYear>1900</DeathYear>
      <IsChanged>false</IsChanged>
      <IsVerified>true</IsVerified>
      <IsCityRecordWrong>false</IsCityRecordWrong>
    </PersonRecord>
  </PersonRecords>
  <Images>
    <string>https://s3.amazonaws.com/bg.ami.com/images/2f92e02cc4e5ca15f3f1e09175a4d640.jpg</string>
  </Images>
  <Latitude>45.520813</Latitude>
  <Longitude>-123.004664</Longitude>
  <IsVerified>true</IsVerified>
</Grave>