<?xml version="1.0" encoding="utf-8"?>
<Grave xmlns:xsi="http://www.w3.org/2001/XMLSchema-instance" xmlns:xsd="http://www.w3.org/2001/XMLSchema">
  <Id>1836958</Id>
  <PersonRecords>
    <PersonRecord>
      <GivenNames>Samuel T</GivenNames>
      <FamilyNames>Stephens</FamilyNames>
      <BirthYear>1851</BirthYear>
      <DeathYear>1940</DeathYear>
      <IsChanged>false</IsChanged>
      <IsVerified>true</IsVerified>
      <IsCityRecordWrong>false</IsCityRecordWrong>
    </PersonRecord>
  </PersonRecords>
  <Images>
    <string>https://s3.amazonaws.com/bg.ami.com/images/382def24bcfb4d5b9370fb72f8cdc3c2.jpg</string>
  </Images>
  <Latitude>45.520785</Latitude>
  <Longitude>-123.005321</Longitude>
  <IsVerified>true</IsVerified>
</Grave>