<?xml version="1.0" encoding="utf-8"?>
<Grave xmlns:xsi="http://www.w3.org/2001/XMLSchema-instance" xmlns:xsd="http://www.w3.org/2001/XMLSchema">
  <Id>1837239</Id>
  <PersonRecords>
    <PersonRecord>
      <GivenNames>John</GivenNames>
      <FamilyNames>Schilling</FamilyNames>
      <BirthYear>1877</BirthYear>
      <DeathYear>1927</DeathYear>
      <IsChanged>false</IsChanged>
      <IsVerified>true</IsVerified>
      <IsCityRecordWrong>false</IsCityRecordWrong>
    </PersonRecord>
  </PersonRecords>
  <Images>
    <string>https://s3.amazonaws.com/bg.ami.com/images/e0f035b68c75ae8be28f492583078041.jpg</string>
  </Images>
  <Information>Father</Information>
  <Latitude>45.52063</Latitude>
  <Longitude>-123.00766</Longitude>
  <IsVerified>true</IsVerified>
</Grave>