<?xml version="1.0" encoding="utf-8"?>
<Grave xmlns:xsi="http://www.w3.org/2001/XMLSchema-instance" xmlns:xsd="http://www.w3.org/2001/XMLSchema">
  <Id>1836754</Id>
  <PersonRecords>
    <PersonRecord>
      <GivenNames>Monta Lee</GivenNames>
      <FamilyNames>Vandehey</FamilyNames>
      <BirthDay>2</BirthDay>
      <BirthMonth>Nov</BirthMonth>
      <BirthYear>1928</BirthYear>
      <DeathDay>3</DeathDay>
      <DeathMonth>Nov</DeathMonth>
      <DeathYear>1928</DeathYear>
      <IsChanged>false</IsChanged>
      <IsVerified>true</IsVerified>
      <IsCityRecordWrong>false</IsCityRecordWrong>
    </PersonRecord>
  </PersonRecords>
  <Images>
    <string>https://s3.amazonaws.com/bg.ami.com/images/1804f677da7bf2ad0f76d2b6a304cd22.jpg</string>
  </Images>
  <Latitude>45.52054</Latitude>
  <Longitude>-123.006745</Longitude>
  <IsVerified>true</IsVerified>
</Grave>